odoo/addons/contract_operating_unit/README.rst
odoo/addons/contract_operating_unit/__init__.py
odoo/addons/contract_operating_unit/__manifest__.py
odoo/addons/contract_operating_unit/i18n/contract_operating_unit.pot
odoo/addons/contract_operating_unit/models/__init__.py
odoo/addons/contract_operating_unit/models/contract.py
odoo/addons/contract_operating_unit/readme/CONTRIBUTORS.rst
odoo/addons/contract_operating_unit/readme/DESCRIPTION.rst
odoo/addons/contract_operating_unit/readme/USAGE.rst
odoo/addons/contract_operating_unit/security/contract_security.xml
odoo/addons/contract_operating_unit/static/description/icon.png
odoo/addons/contract_operating_unit/static/description/index.html
odoo/addons/contract_operating_unit/tests/__init__.py
odoo/addons/contract_operating_unit/tests/test_contract_operating_unit.py
odoo/addons/contract_operating_unit/views/contract_view.xml
odoo14_addon_contract_operating_unit-14.0.1.1.0.dist-info/METADATA
odoo14_addon_contract_operating_unit-14.0.1.1.0.dist-info/WHEEL
odoo14_addon_contract_operating_unit-14.0.1.1.0.dist-info/top_level.txt
odoo14_addon_contract_operating_unit-14.0.1.1.0.dist-info/RECORD
